{
  "_comment": "Machine-readable batch tracker. Update after each session. The routine reads next_stage and the service_city_matrix / city_expansion / country_expansion blocks to pick the next uncompleted block.",
  "autonomy": "Fully autonomous. One block per run, full QA gate, commit to master, post live links to Slack as a record. No approval step, no wait-for-go, no stop condition. When one expansion track completes, move to the next in the order under build_order.",
  "blog": {
    "last_batch_completed": 8,
    "total_articles_live": 108,
    "next_batch": 9,
    "next_blog_batch_topics": [
      "is-lagos-safe-for-business-travel",
      "close-protection-female-executives-middle-east",
      "private-security-regulations-brazil",
      "security-driver-nairobi-vs-taxi",
      "executive-protection-bogota"
    ],
    "target_total": 600,
    "cannibalisation_note": "Do not blog topics already covered by service x city deep pages. Blog covers angles the deep pages do not: cost breakdowns, regulatory explainers, comparisons, question-led safety guides."
  },
  "cities": {
    "total_live": 268,
    "target": 270
  },
  "services": [
    "bodyguard-hire",
    "security-drivers",
    "executive-protection",
    "residential-security",
    "event-security",
    "close-protection-officers",
    "secure-airport-transfers"
  ],
  "service_city_matrix": {
    "_goal": "THE GROWTH ENGINE. Every service silo across every live city. 7 services x 250 target cities = ~1,750 service-city deep pages. Currently all 7 services cover the top 60 cities. Expanding to full city set, one service-city block of 10 pages per run.",
    "priority_cities": [
      "johannesburg",
      "lagos",
      "dubai",
      "nairobi",
      "mexico-city",
      "bogota",
      "riyadh",
      "mumbai",
      "sao-paulo",
      "istanbul"
    ],
    "non_priority_batch1": [
      "london",
      "paris",
      "new-york",
      "singapore",
      "hong-kong",
      "sydney",
      "tokyo",
      "beijing",
      "berlin",
      "cape-town"
    ],
    "batch2_cities": [
      "bangkok",
      "abu-dhabi",
      "amsterdam",
      "kuala-lumpur",
      "madrid",
      "toronto",
      "moscow",
      "doha",
      "vienna",
      "zurich"
    ],
    "batch3_cities": [
      "buenos-aires",
      "cairo",
      "miami",
      "jakarta",
      "auckland",
      "tel-aviv",
      "manila",
      "washington-dc",
      "milan",
      "melbourne"
    ],
    "batch4_cities": [
      "abidjan",
      "abuja",
      "accra",
      "addis-ababa",
      "algiers",
      "almaty",
      "amman",
      "ankara",
      "baghdad",
      "baku"
    ],
    "batch5_cities": [
      "bangalore",
      "delhi",
      "shanghai",
      "casablanca",
      "kyiv",
      "warsaw",
      "montreal",
      "geneva",
      "rome",
      "naples"
    ],
    "blocks": {
      "bodyguard-hire": {
        "status": "BATCH35-DONE",
        "date": "2026-06-27",
        "pages": 268,
        "covered": "all 268 live cities (batch27 added in batch35)",
        "remaining": "SD/EP/RS/ES/CPO/SAT still to cover 10 batch27 cities"
      },
      "security-drivers": {
        "status": "BATCH36-DONE",
        "date": "2026-06-28",
        "pages": 268,
        "covered": "all 268 live cities (batch27 added in batch36)",
        "remaining": "none -- all 268 cities covered"
      },
      "executive-protection": {
        "status": "BATCH36-DONE",
        "date": "2026-06-28",
        "pages": 268,
        "covered": "all 268 live cities (batch27 added in batch36)",
        "remaining": "none -- all 268 cities covered"
      },
      "residential-security": {
        "status": "BATCH36-DONE",
        "date": "2026-06-28",
        "pages": 268,
        "covered": "all 268 live cities (batch27 added in batch36)",
        "remaining": "none -- all 268 cities covered"
      },
      "event-security": {
        "status": "BATCH36-DONE",
        "date": "2026-06-28",
        "pages": 268,
        "covered": "all 268 live cities (batch27 added in batch36)",
        "remaining": "none -- all 268 cities covered"
      },
      "close-protection-officers": {
        "status": "BATCH36-DONE",
        "date": "2026-06-28",
        "pages": 268,
        "covered": "all 268 live cities (batch27 added in batch36)",
        "remaining": "none -- all 268 cities covered"
      },
      "secure-airport-transfers": {
        "status": "BATCH35-DONE",
        "date": "2026-06-27",
        "pages": 258,
        "covered": "all 258 live cities (batch26 added in batch35)",
        "remaining": "none -- all 258 cities covered"
      }
    },
    "expansion_order": "For each service in the services list, build that service across the next 10 live cities not yet covered for it (read cities from site/content/cities/, skip any service-city slug already on disk). Rotate which service is extended each block so the matrix fills evenly: bodyguard-hire batch, then security-drivers batch, then executive-protection, residential-security, event-security, close-protection-officers, secure-airport-transfers, then back to bodyguard-hire for the next 10 cities. One 10-page block per run.",
    "current_coverage_note": "Batch36 (28 Jun 2026): SD/EP/RS/ES/CPO x batch27 (50 pages). All 5 services now cover all 268 live cities. BH/SD/EP/RS/ES/CPO cover 268 cities. SAT still at 258 (batch27 gap: 10 pages). Cities live: 268. Total pages: 2225.",
    "cities_covered_bh": 268,
    "cities_covered_sd": 268,
    "cities_covered_ep": 268,
    "cities_covered_rs": 268,
    "cities_covered_es": 268,
    "cities_covered_cpo": 268,
    "cities_covered_sat": 258,
    "batch27_cities": [
      "florence",
      "turin",
      "seville",
      "toulouse",
      "rotterdam",
      "the-hague",
      "nice",
      "verona",
      "bilbao",
      "palermo"
    ],
    "batch26_cities": [
      "las-palmas",
      "tenerife",
      "thessaloniki",
      "izmir",
      "maracaibo",
      "dammam",
      "medina",
      "nassau",
      "bridgetown",
      "male"
    ],
    "batch25_cities": [
      "astana",
      "bern",
      "las-vegas",
      "krakow",
      "basra",
      "marseille",
      "valencia",
      "kumasi",
      "ibadan",
      "havana"
    ],
    "batch23_cities": [
      "shenzhen",
      "guangzhou",
      "chengdu",
      "monterrey",
      "durban",
      "pune",
      "porto-alegre",
      "barranquilla",
      "surabaya",
      "cebu"
    ],
    "batch24_cities": [
      "port-moresby",
      "lilongwe",
      "mandalay",
      "wuhan",
      "recife",
      "fortaleza",
      "cali",
      "macao",
      "nanjing",
      "sharm-el-sheikh"
    ],
    "batch21_cities": [
      "dallas",
      "seattle",
      "philadelphia",
      "brisbane",
      "perth",
      "calgary",
      "busan",
      "porto",
      "glasgow",
      "denver"
    ],
    "batch22_cities": [
      "seoul",
      "austin",
      "hanoi",
      "phoenix",
      "kolkata",
      "chennai",
      "wellington",
      "adelaide",
      "ottawa",
      "hyderabad"
    ],
    "batch19_cities": [
      "lisbon",
      "brussels",
      "munich",
      "barcelona",
      "frankfurt",
      "hamburg",
      "luxembourg-city",
      "reykjavik",
      "lyon",
      "edinburgh"
    ],
    "batch20_cities": [
      "chicago",
      "los-angeles",
      "san-francisco",
      "houston",
      "manchester",
      "vancouver",
      "osaka",
      "taipei",
      "boston",
      "atlanta"
    ]
  },
  "city_expansion": {
    "_goal": "Grow the city universe to 260+. Each city unlocks 7 new service-city matrix pages, so cities are high-value additions. Build the next 5-10 cities per block from the P4 city queue (next-tier business-travel and high-net-worth destinations: regional capitals, financial centres, and resource/energy hubs not yet covered).",
    "live": 258,
    "target": 260,
    "next_p4_queue": [
      "Bologna",
      "Genoa",
      "Malaga",
      "Valencia-ES",
      "Zaragoza",
      "Rennes",
      "Bordeaux",
      "Eindhoven",
      "Utrecht",
      "Ghent"
    ],
    "_note_p4_queue": "Next 10 European cities for batch28. Batch27 (Florence/Turin/Seville/Toulouse/Rotterdam/The Hague/Nice/Verona/Bilbao/Palermo) complete.",
    "_batch27_completed": [
      "Florence",
      "Turin",
      "Seville",
      "Toulouse",
      "Rotterdam",
      "The Hague",
      "Nice",
      "Verona",
      "Bilbao",
      "Palermo"
    ],
    "_batch25_completed": [
      "Astana",
      "Bern",
      "Las Vegas",
      "Krakow",
      "Basra",
      "Marseille",
      "Valencia",
      "Kumasi",
      "Ibadan",
      "Havana"
    ],
    "_batch24_completed": [
      "Port Moresby",
      "Lilongwe",
      "Mandalay",
      "Wuhan",
      "Recife",
      "Fortaleza",
      "Cali",
      "Macao",
      "Nanjing",
      "Sharm el-Sheikh"
    ],
    "_batch23_completed": [
      "Shenzhen",
      "Guangzhou",
      "Chengdu",
      "Monterrey",
      "Durban",
      "Pune",
      "Porto Alegre",
      "Barranquilla",
      "Surabaya",
      "Cebu"
    ],
    "_batch22_completed": [
      "Seoul",
      "Austin",
      "Hanoi",
      "Phoenix",
      "Kolkata",
      "Chennai",
      "Wellington",
      "Adelaide",
      "Ottawa",
      "Hyderabad"
    ],
    "_batch21_completed": [
      "Dallas",
      "Seattle",
      "Philadelphia",
      "Brisbane",
      "Perth",
      "Calgary",
      "Busan",
      "Porto",
      "Glasgow",
      "Denver"
    ],
    "_completed_batch20_cities": [
      "Chicago",
      "Los Angeles",
      "San Francisco",
      "Houston",
      "Manchester",
      "Vancouver",
      "Osaka",
      "Taipei",
      "Boston",
      "Atlanta"
    ],
    "_completed_batch19_cities": [
      "Lisbon",
      "Brussels",
      "Munich",
      "Barcelona",
      "Frankfurt",
      "Hamburg",
      "Luxembourg City",
      "Reykjavik",
      "Lyon",
      "Edinburgh"
    ],
    "_completed_batch17": [
      "Valletta",
      "Nicosia",
      "Riga",
      "Vilnius",
      "Tallinn",
      "Ljubljana",
      "Zagreb",
      "Bratislava",
      "Sofia",
      "Minsk"
    ],
    "_completed_p4_batch15": [
      "Antananarivo",
      "Port Louis",
      "Victoria-Seychelles",
      "Gaborone",
      "Windhoek",
      "Maseru",
      "Mbabane",
      "Freetown",
      "Monrovia",
      "Ouagadougou"
    ],
    "_completed_p4_batch13": [
      "Kingston",
      "Georgetown",
      "Paramaribo",
      "Port-au-Prince",
      "Tegucigalpa",
      "San Salvador",
      "Guatemala City",
      "Managua",
      "Belize City",
      "Yaounde"
    ],
    "_completed_p4_batch14": [
      "Libreville",
      "Brazzaville",
      "Bangui",
      "Ndjamena",
      "Khartoum",
      "Juba",
      "Asmara",
      "Djibouti City",
      "Hargeisa",
      "Bujumbura"
    ],
    "batch16_completed": [
      "Malabo",
      "Lome",
      "Cotonou",
      "Praia",
      "Yerevan",
      "Chisinau",
      "Tirana",
      "Podgorica",
      "Sarajevo",
      "Skopje"
    ],
    "_completed_batch18": [
      "Bucharest",
      "Prague",
      "Budapest",
      "Belgrade",
      "Athens",
      "Helsinki",
      "Stockholm",
      "Oslo",
      "Copenhagen",
      "Dublin"
    ],
    "_batch26_completed": [
      "Las Palmas de Gran Canaria",
      "Tenerife",
      "Thessaloniki",
      "Izmir",
      "Maracaibo",
      "Dammam",
      "Medina",
      "Nassau",
      "Bridgetown",
      "Male"
    ]
  },
  "country_expansion": {
    "_goal": "Grow country hubs from 38 to ~120 so every city has a parent country hub and the site captures country-level close-protection queries. Build the next 5 country hubs per block for any country that has live cities but no hub yet.",
    "live": 38,
    "target": 120
  },
  "build_order": [
    "1. service_city_matrix: default every run. Extend the next service across its next 10 uncovered cities. This is the priority growth track.",
    "2. city_expansion: when a service_city_matrix block for the current rotation is already committed, build the next 5-10 P4 cities (which then feed the matrix).",
    "3. country_expansion: build the next 5 country hubs for countries with live cities but no hub.",
    "4. blog: when the next matrix/city/country block is already committed, build the next 5-article blog batch from the keyword matrix (non-cannibalising angles)."
  ],
  "pages": {
    "total_live": 2225,
    "_count_note": "2175 prior + 50 new (batch36: SD/EP/RS/ES/CPO x batch27). BH/SD/EP/RS/ES/CPO cover 268 cities; SAT covers 258.",
    "last_updated": "2026-06-28"
  },
  "engine_alignment": {
    "1_combinatorial_generators": "DONE",
    "2_structured_data_layer": "DONE",
    "3_bulk_blog_factory": "IN PROGRESS - 108 articles live, target 600",
    "4_internal_link_graph": "DONE (floor). Re-run scripts/rebuild_link_graph.py after each matrix batch so new service-city pages are linked from their city and service-silo parents.",
    "5_qa_seo_quality_gate": "GREEN. 0 errors across all 50 batch32 pages (6 advisory warnings, pre-existing).",
    "6_incremental_deploy_pipeline": "DONE",
    "7_operating_system": "DONE"
  },
  "cannibalisation_rule": "Do not blog on topics already covered by service x city deep pages. The deep pages ARE the definitive content for {service}/{city}. Blog covers angles the deep pages do not.",
  "next_stage": "BATCH36 COMPLETE (28 Jun 2026): SD/EP/RS/ES/CPO x batch27 (50 pages). BH/SD/EP/RS/ES/CPO now cover all 268 live cities. SAT still at 258 (batch27 gap). Cities live: 268. Total: 2225 pages. Next: SAT x batch27 (10 pages) + city expansion batch28 (Bologna, Genoa, Malaga, Zaragoza, Rennes, Bordeaux, Eindhoven, Utrecht, Ghent + 1 more) + BH/SD/EP/RS x batch28 cities."
}